pydev_app_engine_debug_startup.py
pydev_run_in_console.py
pydevconsole.py
pydevd.py
pydevd_file_utils.py
pydevd_tracing.py
setup_pydevd_cython.py
_pydev_bundle/__init__.py
_pydev_bundle/_pydev_calltip_util.py
_pydev_bundle/_pydev_completer.py
_pydev_bundle/_pydev_execfile.py
_pydev_bundle/_pydev_filesystem_encoding.py
_pydev_bundle/_pydev_getopt.py
_pydev_bundle/_pydev_imports_tipper.py
_pydev_bundle/_pydev_jy_imports_tipper.py
_pydev_bundle/_pydev_log.py
_pydev_bundle/_pydev_saved_modules.py
_pydev_bundle/_pydev_sys_patch.py
_pydev_bundle/_pydev_tipper_common.py
_pydev_bundle/pydev_console_utils.py
_pydev_bundle/pydev_import_hook.py
_pydev_bundle/pydev_imports.py
_pydev_bundle/pydev_ipython_console.py
_pydev_bundle/pydev_ipython_console_011.py
_pydev_bundle/pydev_is_thread_alive.py
_pydev_bundle/pydev_localhost.py
_pydev_bundle/pydev_log.py
_pydev_bundle/pydev_monkey.py
_pydev_bundle/pydev_monkey_qt.py
_pydev_bundle/pydev_override.py
_pydev_bundle/pydev_umd.py
_pydev_bundle/pydev_versioncheck.py
_pydev_bundle/fsnotify/__init__.py
_pydev_runfiles/__init__.py
_pydev_runfiles/pydev_runfiles.py
_pydev_runfiles/pydev_runfiles_coverage.py
_pydev_runfiles/pydev_runfiles_nose.py
_pydev_runfiles/pydev_runfiles_parallel.py
_pydev_runfiles/pydev_runfiles_parallel_client.py
_pydev_runfiles/pydev_runfiles_pytest2.py
_pydev_runfiles/pydev_runfiles_unittest.py
_pydev_runfiles/pydev_runfiles_xml_rpc.py
_pydevd_bundle/__init__.py
_pydevd_bundle/pydevconsole_code.py
_pydevd_bundle/pydevd_additional_thread_info.py
_pydevd_bundle/pydevd_additional_thread_info_regular.py
_pydevd_bundle/pydevd_api.py
_pydevd_bundle/pydevd_breakpoints.py
_pydevd_bundle/pydevd_bytecode_utils.py
_pydevd_bundle/pydevd_bytecode_utils_py311.py
_pydevd_bundle/pydevd_code_to_source.py
_pydevd_bundle/pydevd_collect_bytecode_info.py
_pydevd_bundle/pydevd_comm.py
_pydevd_bundle/pydevd_comm_constants.py
_pydevd_bundle/pydevd_command_line_handling.py
_pydevd_bundle/pydevd_console.py
pydevd-3.4.1.dist-info/LICENSE-EPL
pydevd-3.4.1.dist-info/METADATA
pydevd-3.4.1.dist-info/WHEEL
pydevd-3.4.1.dist-info/entry_points.txt
pydevd-3.4.1.dist-info/top_level.txt
pydevd-3.4.1.dist-info/RECORD
