Metadata-Version: 2.1
Name: pydevd
Version: 3.4.1
Summary: PyDev.Debugger (used in PyDev, PyCharm and VSCode Python)
Home-page: https://github.com/fabioz/PyDev.Debugger/
Author: Fabio Zadrozny and others
License: EPL
Keywords: pydev,pydevd,pydev.debugger
Classifier: Development Status :: 6 - Mature
Classifier: Environment :: Console
Classifier: Intended Audience :: Developers
Classifier: License :: OSI Approved :: Eclipse Public License 1.0 (EPL-1.0)
Classifier: Operating System :: MacOS :: MacOS X
Classifier: Operating System :: Microsoft :: Windows
Classifier: Operating System :: POSIX
Classifier: Programming Language :: Python
Classifier: Programming Language :: Python :: 3
Classifier: Programming Language :: Python :: 3.8
Classifier: Programming Language :: Python :: 3.9
Classifier: Programming Language :: Python :: 3.10
Classifier: Programming Language :: Python :: 3.11
Classifier: Programming Language :: Python :: 3.12
Classifier: Topic :: Software Development :: Debuggers
License-File: LICENSE-EPL
